{"name":"build-javascript","namedChunkGroups":{"polyfill":{"name":"polyfill","assets":[{"name":"webpack-runtime-39994387108e62d059ca.js","size":3968},{"name":"polyfill-a692333e6a68208f7532.js","size":85029}],"filteredAssets":0,"assetsSize":88997,"filteredAuxiliaryAssets":2,"auxiliaryAssetsSize":226762},"app":{"name":"app","assets":[{"name":"webpack-runtime-39994387108e62d059ca.js","size":3968},{"name":"framework-2bcf2aafce2802073c37.js","size":141416},{"name":"styles.e0d6dfaf88cb7027a534.css","size":145010},{"name":"app-a08fc8ecd6ca5fed1a91.js","size":985519}],"filteredAssets":0,"assetsSize":1275913,"filteredAuxiliaryAssets":49,"auxiliaryAssetsSize":3905809},"component---src-pages-blog-mdx-frontmatter-slug-tsx":{"name":"component---src-pages-blog-mdx-frontmatter-slug-tsx","assets":[{"name":"commons-458aae609ddf0d665c63.js","size":39188},{"name":"component---src-pages-blog-mdx-frontmatter-slug-tsx-810979c4a3c43da97c53.js","size":4195}],"filteredAssets":0,"assetsSize":43383,"filteredAuxiliaryAssets":2,"auxiliaryAssetsSize":173709},"component---src-pages-index-tsx":{"name":"component---src-pages-index-tsx","assets":[{"name":"a39c196d-da9b56062c06437e3594.js","size":1964},{"name":"commons-458aae609ddf0d665c63.js","size":39188},{"name":"component---src-pages-index-tsx-ecb617d6af6cdd299a79.js","size":1680}],"filteredAssets":0,"assetsSize":42832,"filteredAuxiliaryAssets":3,"auxiliaryAssetsSize":176199}},"assetsByChunkName":{"polyfill":["webpack-runtime-39994387108e62d059ca.js","polyfill-a692333e6a68208f7532.js"],"app":["webpack-runtime-39994387108e62d059ca.js","framework-2bcf2aafce2802073c37.js","styles.e0d6dfaf88cb7027a534.css","app-a08fc8ecd6ca5fed1a91.js"],"component---src-pages-blog-mdx-frontmatter-slug-tsx":["commons-458aae609ddf0d665c63.js","component---src-pages-blog-mdx-frontmatter-slug-tsx-810979c4a3c43da97c53.js"],"component---src-pages-index-tsx":["a39c196d-da9b56062c06437e3594.js","commons-458aae609ddf0d665c63.js","component---src-pages-index-tsx-ecb617d6af6cdd299a79.js"]},"childAssetsByChunkName":{}}